LICENSE
MANIFEST.in
README.rst
setup.py
tests.py
FeinCMS_Template_Content.egg-info/PKG-INFO
FeinCMS_Template_Content.egg-info/SOURCES.txt
FeinCMS_Template_Content.egg-info/dependency_links.txt
FeinCMS_Template_Content.egg-info/requires.txt
FeinCMS_Template_Content.egg-info/top_level.txt
feincms_template_content/__init__.py
feincms_template_content/admin.py
feincms_template_content/models.py
feincms_template_content/content/__init__.py
feincms_template_content/content/base_image.py
feincms_template_content/content/image.py
feincms_template_content/content/medialibrary_image.py
feincms_template_content/content/rich_text.py
feincms_template_content/templates/content/rich_text.html
feincms_template_content/templates/content/image/block.html
feincms_template_content/templates/content/image/float_left.html
feincms_template_content/templates/content/image/float_right.html
testapp/__init__.py
testapp/models.py