Metadata-Version: 1.0
Name: FeinCMS-Template-Content
Version: 0.0.5
Summary: FeinCMS content types with (optionally) selectable templates.
Home-page: https://github.com/RichardOfWard/feincms-template-content
Author: Richard Ward
Author-email: richard@richard.ward.name
License: MIT License
Platform: UNKNOWN
